copier_template_tester/__init__.py
copier_template_tester/_config.py
copier_template_tester/_pre_commit_support.py
copier_template_tester/_runtime_type_check_setup.py
copier_template_tester/_write_output.py
copier_template_tester/main.py
copier_template_tester/py.typed
copier_template_tester-2.2.0.dist-info/LICENSE
copier_template_tester-2.2.0.dist-info/METADATA
copier_template_tester-2.2.0.dist-info/WHEEL
copier_template_tester-2.2.0.dist-info/entry_points.txt
copier_template_tester-2.2.0.dist-info/RECORD
