Metadata-Version: 2.3
Name: copier_template_tester
Version: 2.2.0
Summary: Test copier templates
License: MIT
Keywords: calcipy_template
Author: Kyle King
Author-email: dev.act.kyle@gmail.com
Requires-Python: >=3.10.9,<4.0.0
Classifier: Development Status :: 6 - Mature
Classifier: License :: OSI Approved :: MIT License
Classifier: Operating System :: OS Independent
Classifier: Programming Language :: Python :: 3
Classifier: Programming Language :: Python :: 3.11
Classifier: Programming Language :: Python :: 3.12
Classifier: Programming Language :: Python :: 3.13
Classifier: Programming Language :: Python :: 3.10
Requires-Dist: copier (>=9.2.0)
Requires-Dist: corallium (>=2.1.1)
Project-URL: Bug Tracker, https://github.com/kyleking/copier-template-tester/issues
Project-URL: Changelog, https://github.com/kyleking/copier-template-tester/blob/main/docs/docs/CHANGELOG.md
Project-URL: Documentation, https://copier-template-tester.kyleking.me
Project-URL: Repository, https://github.com/kyleking/copier-template-tester
